{
 "custom_fields": [
  {
   "_assign": null,
   "_comments": null,
   "_liked_by": null,
   "_user_tags": null,
   "allow_in_quick_entry": 0,
   "allow_on_submit": 1,
   "bold": 0,
   "collapsible": 0,
   "collapsible_depends_on": null,
   "columns": 0,
   "creation": "2017-04-21 15:34:00.718285",
   "default": null,
   "depends_on": null,
   "description": null,
   "docstatus": 0,
   "dt": "Material Request Item",
   "fetch_from": null,
   "fetch_if_empty": 0,
   "fieldname": "stock",
   "fieldtype": "Check",
   "hidden": 0,
   "idx": 72,
   "ignore_user_permissions": 0,
   "ignore_xss_filter": 0,
   "in_filter": 0,
   "in_filter_dash": 0,
   "in_global_search": 0,
   "in_list_view": 0,
   "in_standard_filter": 0,
   "insert_after": "page_break",
   "label": "Stock",
   "length": 0,
   "modified": "2017-04-21 15:34:00.718285",
   "modified_by": "Administrator",
   "name": "Material Request Item-stock",
   "no_copy": 0,
   "options": null,
   "owner": "Administrator",
   "parent": null,
   "parentfield": null,
   "parenttype": null,
   "permlevel": 0,
   "precision": "",
   "print_hide": 0,
   "print_hide_if_no_value": 0,
   "print_width": null,
   "read_only": 0,
   "report_hide": 0,
   "reqd": 0,
   "search_index": 0,
   "translatable": 1,
   "unique": 0,
   "width": "50"
  },
  {
   "_assign": null,
   "_comments": null,
   "_liked_by": null,
   "_user_tags": null,
   "allow_in_quick_entry": 0,
   "allow_on_submit": 1,
   "bold": 0,
   "collapsible": 0,
   "collapsible_depends_on": null,
   "columns": 0,
   "creation": "2017-06-09 16:43:53.185080",
   "default": null,
   "depends_on": null,
   "description": null,
   "docstatus": 0,
   "dt": "Material Request Item",
   "fetch_from": null,
   "fetch_if_empty": 0,
   "fieldname": "status",
   "fieldtype": "Select",
   "hidden": 0,
   "idx": 74,
   "ignore_user_permissions": 0,
   "ignore_xss_filter": 0,
   "in_filter": 0,
   "in_filter_dash": 0,
   "in_global_search": 0,
   "in_list_view": 1,
   "in_standard_filter": 0,
   "insert_after": "workstations",
   "label": "Status",
   "length": 0,
   "modified": "2017-06-09 16:43:53.185080",
   "modified_by": "Administrator",
   "name": "Material Request Item-status",
   "no_copy": 0,
   "options": "\n-\nPending\nStarted\nCompleted",
   "owner": "Administrator",
   "parent": null,
   "parentfield": null,
   "parenttype": null,
   "permlevel": 0,
   "precision": "",
   "print_hide": 0,
   "print_hide_if_no_value": 0,
   "print_width": null,
   "read_only": 0,
   "report_hide": 0,
   "reqd": 0,
   "search_index": 0,
   "translatable": 1,
   "unique": 0,
   "width": null
  },
  {
   "_assign": null,
   "_comments": null,
   "_liked_by": null,
   "_user_tags": null,
   "allow_in_quick_entry": 0,
   "allow_on_submit": 1,
   "bold": 0,
   "collapsible": 0,
   "collapsible_depends_on": null,
   "columns": 0,
   "creation": "2017-06-09 21:27:24.585575",
   "default": null,
   "depends_on": null,
   "description": null,
   "docstatus": 0,
   "dt": "Material Request Item",
   "fetch_from": null,
   "fetch_if_empty": 0,
   "fieldname": "tech_descr",
   "fieldtype": "Text",
   "hidden": 0,
   "idx": 75,
   "ignore_user_permissions": 0,
   "ignore_xss_filter": 0,
   "in_filter": 0,
   "in_filter_dash": 0,
   "in_global_search": 0,
   "in_list_view": 0,
   "in_standard_filter": 0,
   "insert_after": "status",
   "label": "Tech_Descr",
   "length": 0,
   "modified": "2017-06-09 21:27:24.585575",
   "modified_by": "Administrator",
   "name": "Material Request Item-tech_descr",
   "no_copy": 0,
   "options": null,
   "owner": "Administrator",
   "parent": null,
   "parentfield": null,
   "parenttype": null,
   "permlevel": 0,
   "precision": "",
   "print_hide": 0,
   "print_hide_if_no_value": 0,
   "print_width": null,
   "read_only": 0,
   "report_hide": 0,
   "reqd": 0,
   "search_index": 0,
   "translatable": 1,
   "unique": 0,
   "width": null
  },
  {
   "_assign": null,
   "_comments": null,
   "_liked_by": null,
   "_user_tags": null,
   "allow_in_quick_entry": 0,
   "allow_on_submit": 0,
   "bold": 0,
   "collapsible": 0,
   "collapsible_depends_on": null,
   "columns": 0,
   "creation": "2019-02-06 16:37:01.471900",
   "default": null,
   "depends_on": null,
   "description": null,
   "docstatus": 0,
   "dt": "Material Request Item",
   "fetch_from": null,
   "fetch_if_empty": 0,
   "fieldname": "ws",
   "fieldtype": "Select",
   "hidden": 0,
   "idx": 76,
   "ignore_user_permissions": 0,
   "ignore_xss_filter": 0,
   "in_filter": 0,
   "in_filter_dash": 0,
   "in_global_search": 0,
   "in_list_view": 0,
   "in_standard_filter": 0,
   "insert_after": "tech_descr",
   "label": "ws",
   "length": 0,
   "modified": "2019-02-06 16:37:01.471900",
   "modified_by": "Administrator",
   "name": "Material Request Item-ws",
   "no_copy": 0,
   "options": "\n\u0637\u0628\u064a\u0639\u064a\n\u0635\u0646\u0627\u0639\u064a\n\u062a\u0646\u062c\u064a\u062f\n\u0645\u0633\u062a\u0648\u0631\u062f\n\u062a\u0646\u062c\u064a\u062f - \u0637\u0628\u064a\u0639\u064a\n\u0635\u0646\u0627\u0639\u064a - \u0637\u0628\u064a\u0639\u064a\n\u0635\u0646\u0627\u0639\u064a - \u062a\u0646\u062c\u064a\u062f\n\u0635\u0646\u0627\u0639\u064a - \u0645\u0639\u0627\u062f\u0646\n\u0635\u0646\u0627\u0639\u064a - \u0645\u0648\u0631\u062f \u062e\u0627\u0631\u062c\u064a\n\u0645\u0639\u0627\u062f\u0646\n\u0645\u0648\u0631\u062f \u062e\u0627\u0631\u062c\u064a\n\u0637\u0628\u064a\u0639\u064a - \u0645\u0639\u0627\u062f\u0646\n",
   "owner": "Administrator",
   "parent": null,
   "parentfield": null,
   "parenttype": null,
   "permlevel": 0,
   "precision": "",
   "print_hide": 0,
   "print_hide_if_no_value": 0,
   "print_width": null,
   "read_only": 0,
   "report_hide": 0,
   "reqd": 0,
   "search_index": 0,
   "translatable": 1,
   "unique": 0,
   "width": null
  },
  {
   "_assign": null,
   "_comments": null,
   "_liked_by": null,
   "_user_tags": null,
   "allow_in_quick_entry": 0,
   "allow_on_submit": 1,
   "bold": 0,
   "collapsible": 0,
   "collapsible_depends_on": null,
   "columns": 0,
   "creation": "2019-02-06 16:40:55.145205",
   "default": null,
   "depends_on": null,
   "description": null,
   "docstatus": 0,
   "dt": "Material Request Item",
   "fetch_from": null,
   "fetch_if_empty": 0,
   "fieldname": "workstations",
   "fieldtype": "Link",
   "hidden": 0,
   "idx": 73,
   "ignore_user_permissions": 0,
   "ignore_xss_filter": 0,
   "in_filter": 0,
   "in_filter_dash": 0,
   "in_global_search": 0,
   "in_list_view": 1,
   "in_standard_filter": 0,
   "insert_after": "stock",
   "label": "workstations",
   "length": 0,
   "modified": "2019-02-06 16:40:55.145205",
   "modified_by": "Administrator",
   "name": "Material Request Item-workstations",
   "no_copy": 0,
   "options": "Workstation",
   "owner": "Administrator",
   "parent": null,
   "parentfield": null,
   "parenttype": null,
   "permlevel": 0,
   "precision": "",
   "print_hide": 0,
   "print_hide_if_no_value": 0,
   "print_width": null,
   "read_only": 0,
   "report_hide": 0,
   "reqd": 0,
   "search_index": 0,
   "translatable": 1,
   "unique": 0,
   "width": null
  },
  {
   "_assign": null,
   "_comments": null,
   "_liked_by": null,
   "_user_tags": null,
   "allow_in_quick_entry": 0,
   "allow_on_submit": 1,
   "bold": 0,
   "collapsible": 0,
   "collapsible_depends_on": null,
   "columns": 0,
   "creation": "2019-02-13 15:01:22.069876",
   "default": null,
   "depends_on": null,
   "description": null,
   "docstatus": 0,
   "dt": "Material Request Item",
   "fetch_from": null,
   "fetch_if_empty": 0,
   "fieldname": "accessories",
   "fieldtype": "Check",
   "hidden": 0,
   "idx": 29,
   "ignore_user_permissions": 0,
   "ignore_xss_filter": 0,
   "in_filter": 0,
   "in_filter_dash": 0,
   "in_global_search": 0,
   "in_list_view": 0,
   "in_standard_filter": 0,
   "insert_after": "section_break_4",
   "label": "Accessories",
   "length": 0,
   "modified": "2019-02-13 15:01:22.069876",
   "modified_by": "Administrator",
   "name": "Material Request Item-accessories",
   "no_copy": 0,
   "options": null,
   "owner": "Administrator",
   "parent": null,
   "parentfield": null,
   "parenttype": null,
   "permlevel": 0,
   "precision": "",
   "print_hide": 0,
   "print_hide_if_no_value": 0,
   "print_width": null,
   "read_only": 0,
   "report_hide": 0,
   "reqd": 0,
   "search_index": 0,
   "translatable": 1,
   "unique": 0,
   "width": null
  },
  {
   "_assign": null,
   "_comments": null,
   "_liked_by": null,
   "_user_tags": null,
   "allow_in_quick_entry": 0,
   "allow_on_submit": 1,
   "bold": 0,
   "collapsible": 0,
   "collapsible_depends_on": null,
   "columns": 0,
   "creation": "2019-02-13 15:01:36.079654",
   "default": null,
   "depends_on": null,
   "description": null,
   "docstatus": 0,
   "dt": "Material Request Item",
   "fetch_from": null,
   "fetch_if_empty": 0,
   "fieldname": "glass",
   "fieldtype": "Check",
   "hidden": 0,
   "idx": 30,
   "ignore_user_permissions": 0,
   "ignore_xss_filter": 0,
   "in_filter": 0,
   "in_filter_dash": 0,
   "in_global_search": 0,
   "in_list_view": 0,
   "in_standard_filter": 0,
   "insert_after": "accessories",
   "label": "Glass",
   "length": 0,
   "modified": "2019-02-13 15:01:36.079654",
   "modified_by": "Administrator",
   "name": "Material Request Item-glass",
   "no_copy": 0,
   "options": null,
   "owner": "Administrator",
   "parent": null,
   "parentfield": null,
   "parenttype": null,
   "permlevel": 0,
   "precision": "",
   "print_hide": 0,
   "print_hide_if_no_value": 0,
   "print_width": null,
   "read_only": 0,
   "report_hide": 0,
   "reqd": 0,
   "search_index": 0,
   "translatable": 1,
   "unique": 0,
   "width": null
  },
  {
   "_assign": null,
   "_comments": null,
   "_liked_by": null,
   "_user_tags": null,
   "allow_in_quick_entry": 0,
   "allow_on_submit": 0,
   "bold": 0,
   "collapsible": 0,
   "collapsible_depends_on": null,
   "columns": 0,
   "creation": "2019-03-18 13:34:26.614893",
   "default": null,
   "depends_on": null,
   "description": null,
   "docstatus": 0,
   "dt": "Material Request Item",
   "fetch_from": null,
   "fetch_if_empty": 0,
   "fieldname": "notes",
   "fieldtype": "Data",
   "hidden": 0,
   "idx": 18,
   "ignore_user_permissions": 0,
   "ignore_xss_filter": 0,
   "in_filter": 0,
   "in_filter_dash": 0,
   "in_global_search": 0,
   "in_list_view": 0,
   "in_standard_filter": 0,
   "insert_after": "item_name",
   "label": "Notes",
   "length": 0,
   "modified": "2019-03-18 13:34:26.614893",
   "modified_by": "Administrator",
   "name": "Material Request Item-notes",
   "no_copy": 0,
   "options": null,
   "owner": "Administrator",
   "parent": null,
   "parentfield": null,
   "parenttype": null,
   "permlevel": 0,
   "precision": "",
   "print_hide": 0,
   "print_hide_if_no_value": 0,
   "print_width": null,
   "read_only": 0,
   "report_hide": 0,
   "reqd": 0,
   "search_index": 0,
   "translatable": 1,
   "unique": 0,
   "width": null
  },
  {
   "_assign": null,
   "_comments": null,
   "_liked_by": null,
   "_user_tags": null,
   "allow_in_quick_entry": 0,
   "allow_on_submit": 0,
   "bold": 0,
   "collapsible": 0,
   "collapsible_depends_on": null,
   "columns": 0,
   "creation": "2019-05-10 20:32:33.475406",
   "default": null,
   "depends_on": null,
   "description": null,
   "docstatus": 0,
   "dt": "Material Request Item",
   "fetch_from": null,
   "fetch_if_empty": 0,
   "fieldname": "base",
   "fieldtype": "Check",
   "hidden": 1,
   "idx": 2,
   "ignore_user_permissions": 0,
   "ignore_xss_filter": 0,
   "in_filter": 0,
   "in_filter_dash": 0,
   "in_global_search": 0,
   "in_list_view": 0,
   "in_standard_filter": 0,
   "insert_after": "item_code",
   "label": "Base",
   "length": 0,
   "modified": "2019-05-10 20:32:33.475406",
   "modified_by": "Administrator",
   "name": "Material Request Item-base",
   "no_copy": 0,
   "options": null,
   "owner": "Administrator",
   "parent": null,
   "parentfield": null,
   "parenttype": null,
   "permlevel": 0,
   "precision": "",
   "print_hide": 0,
   "print_hide_if_no_value": 0,
   "print_width": null,
   "read_only": 0,
   "report_hide": 0,
   "reqd": 0,
   "search_index": 0,
   "translatable": 0,
   "unique": 0,
   "width": null
  },
  {
   "_assign": null,
   "_comments": null,
   "_liked_by": null,
   "_user_tags": null,
   "allow_in_quick_entry": 0,
   "allow_on_submit": 0,
   "bold": 0,
   "collapsible": 0,
   "collapsible_depends_on": null,
   "columns": 0,
   "creation": "2019-05-10 20:32:52.916862",
   "default": null,
   "depends_on": "eval:doc.base ==1",
   "description": null,
   "docstatus": 0,
   "dt": "Material Request Item",
   "fetch_from": null,
   "fetch_if_empty": 0,
   "fieldname": "base_color",
   "fieldtype": "Link",
   "hidden": 0,
   "idx": 3,
   "ignore_user_permissions": 0,
   "ignore_xss_filter": 0,
   "in_filter": 0,
   "in_filter_dash": 0,
   "in_global_search": 0,
   "in_list_view": 0,
   "in_standard_filter": 0,
   "insert_after": "base",
   "label": "Base Color",
   "length": 0,
   "modified": "2019-05-10 20:32:52.916862",
   "modified_by": "Administrator",
   "name": "Material Request Item-base_color",
   "no_copy": 0,
   "options": "Base Color",
   "owner": "Administrator",
   "parent": null,
   "parentfield": null,
   "parenttype": null,
   "permlevel": 0,
   "precision": "",
   "print_hide": 0,
   "print_hide_if_no_value": 0,
   "print_width": null,
   "read_only": 0,
   "report_hide": 0,
   "reqd": 0,
   "search_index": 0,
   "translatable": 0,
   "unique": 0,
   "width": null
  },
  {
   "_assign": null,
   "_comments": null,
   "_liked_by": null,
   "_user_tags": null,
   "allow_in_quick_entry": 0,
   "allow_on_submit": 0,
   "bold": 0,
   "collapsible": 0,
   "collapsible_depends_on": null,
   "columns": 0,
   "creation": "2019-05-10 20:32:53.205285",
   "default": null,
   "depends_on": "eval:in_list([\"Dino Counter\",\"Dino Desks\",\"Dino Drawers\",\"Dino High Cabinets\",\"Dino Low Cabinets\",\"Dino Meeting Corners\",\"Dino Tables\",\"Dino\",\"Milano\",\"Milano Desks\",\"Milano High Cabinets\",\"Milano Tables\",\"Partition_New\",\"Partition_Seperator_3\",\"Partition_Seperator_6\",\"Partition_Seperator_8\",\"Steel Separator\",\"Steel Workstations\",\"Steel\"], doc.item_group)",
   "description": null,
   "docstatus": 0,
   "dt": "Material Request Item",
   "fetch_from": null,
   "fetch_if_empty": 0,
   "fieldname": "hpl",
   "fieldtype": "Link",
   "hidden": 0,
   "idx": 6,
   "ignore_user_permissions": 0,
   "ignore_xss_filter": 0,
   "in_filter": 0,
   "in_filter_dash": 0,
   "in_global_search": 0,
   "in_list_view": 0,
   "in_standard_filter": 0,
   "insert_after": "metal_color",
   "label": "HPL",
   "length": 0,
   "modified": "2019-05-10 20:32:53.205285",
   "modified_by": "Administrator",
   "name": "Material Request Item-hpl",
   "no_copy": 0,
   "options": "HPL",
   "owner": "Administrator",
   "parent": null,
   "parentfield": null,
   "parenttype": null,
   "permlevel": 0,
   "precision": "",
   "print_hide": 0,
   "print_hide_if_no_value": 0,
   "print_width": null,
   "read_only": 0,
   "report_hide": 0,
   "reqd": 0,
   "search_index": 0,
   "translatable": 0,
   "unique": 0,
   "width": null
  },
  {
   "_assign": null,
   "_comments": null,
   "_liked_by": null,
   "_user_tags": null,
   "allow_in_quick_entry": 0,
   "allow_on_submit": 0,
   "bold": 0,
   "collapsible": 0,
   "collapsible_depends_on": null,
   "columns": 0,
   "creation": "2019-05-10 20:33:11.008023",
   "default": null,
   "depends_on": "eval:in_list([\"\u0635\u0646\u0627\u0639\u064a - \u062a\u0646\u062c\u064a\u062f - \u0645\u0633\u062a\u0648\u0631\u062f\", \"\u0635\u0646\u0627\u0639\u064a - \u062a\u0646\u062c\u064a\u062f - \u0645\u0648\u0631\u062f \u062e\u0627\u0631\u062c\u064a\", \"\u0637\u0628\u064a\u0639\u064a - \u062a\u0646\u062c\u064a\u062f - \u0635\u0646\u0627\u0639\u064a\", \"\u0637\u0628\u064a\u0639\u064a - \u062a\u0646\u062c\u064a\u062f - \u0645\u0633\u062a\u0648\u0631\u062f\", \"\u062a\u0646\u062c\u064a\u062f - \u0637\u0628\u064a\u0639\u064a - \u0645\u0633\u062a\u0648\u0631\u062f - \u0645\u0648\u0631\u062f \u062e\u0627\u0631\u062c\u064a\", \"\u0645\u0633\u062a\u0648\u0631\u062f - \u062a\u0646\u062c\u064a\u062f\", \"\u062a\u0646\u062c\u064a\u062f - \u0637\u0628\u064a\u0639\u064a\", \"\u062a\u0646\u062c\u064a\u062f\", \"\u0635\u0646\u0627\u0639\u064a - \u062a\u0646\u062c\u064a\u062f\"], doc.workstations)",
   "description": null,
   "docstatus": 0,
   "dt": "Material Request Item",
   "fetch_from": null,
   "fetch_if_empty": 0,
   "fieldname": "leather_color",
   "fieldtype": "Link",
   "hidden": 0,
   "idx": 7,
   "ignore_user_permissions": 0,
   "ignore_xss_filter": 0,
   "in_filter": 0,
   "in_filter_dash": 0,
   "in_global_search": 0,
   "in_list_view": 0,
   "in_standard_filter": 0,
   "insert_after": "hpl",
   "label": "Leather Color",
   "length": 0,
   "modified": "2019-05-10 20:33:11.008023",
   "modified_by": "Administrator",
   "name": "Material Request Item-leather_color",
   "no_copy": 0,
   "options": "Leather Color",
   "owner": "Administrator",
   "parent": null,
   "parentfield": null,
   "parenttype": null,
   "permlevel": 0,
   "precision": "",
   "print_hide": 0,
   "print_hide_if_no_value": 0,
   "print_width": null,
   "read_only": 0,
   "report_hide": 0,
   "reqd": 0,
   "search_index": 0,
   "translatable": 0,
   "unique": 0,
   "width": null
  },
  {
   "_assign": null,
   "_comments": null,
   "_liked_by": null,
   "_user_tags": null,
   "allow_in_quick_entry": 0,
   "allow_on_submit": 0,
   "bold": 0,
   "collapsible": 0,
   "collapsible_depends_on": null,
   "columns": 0,
   "creation": "2019-05-10 20:33:11.314454",
   "default": null,
   "depends_on": "eval:doc.item_group == \"New Stone\"",
   "description": null,
   "docstatus": 0,
   "dt": "Material Request Item",
   "fetch_from": null,
   "fetch_if_empty": 0,
   "fieldname": "new_stone",
   "fieldtype": "Link",
   "hidden": 0,
   "idx": 8,
   "ignore_user_permissions": 0,
   "ignore_xss_filter": 0,
   "in_filter": 0,
   "in_filter_dash": 0,
   "in_global_search": 0,
   "in_list_view": 0,
   "in_standard_filter": 0,
   "insert_after": "leather_color",
   "label": "New_Stone",
   "length": 0,
   "modified": "2019-05-10 20:33:11.314454",
   "modified_by": "Administrator",
   "name": "Material Request Item-new_stone",
   "no_copy": 0,
   "options": "New_Stone",
   "owner": "Administrator",
   "parent": null,
   "parentfield": null,
   "parenttype": null,
   "permlevel": 0,
   "precision": "",
   "print_hide": 0,
   "print_hide_if_no_value": 0,
   "print_width": null,
   "read_only": 0,
   "report_hide": 0,
   "reqd": 0,
   "search_index": 0,
   "translatable": 0,
   "unique": 0,
   "width": null
  },
  {
   "_assign": null,
   "_comments": null,
   "_liked_by": null,
   "_user_tags": null,
   "allow_in_quick_entry": 0,
   "allow_on_submit": 0,
   "bold": 0,
   "collapsible": 0,
   "collapsible_depends_on": null,
   "columns": 0,
   "creation": "2019-05-10 20:33:31.888880",
   "default": null,
   "depends_on": "eval:doc.item_group == \"Or Collection\"",
   "description": null,
   "docstatus": 0,
   "dt": "Material Request Item",
   "fetch_from": null,
   "fetch_if_empty": 0,
   "fieldname": "or",
   "fieldtype": "Link",
   "hidden": 0,
   "idx": 9,
   "ignore_user_permissions": 0,
   "ignore_xss_filter": 0,
   "in_filter": 0,
   "in_filter_dash": 0,
   "in_global_search": 0,
   "in_list_view": 0,
   "in_standard_filter": 0,
   "insert_after": "new_stone",
   "label": "OR",
   "length": 0,
   "modified": "2019-05-10 20:33:31.888880",
   "modified_by": "Administrator",
   "name": "Material Request Item-or",
   "no_copy": 0,
   "options": "OR",
   "owner": "Administrator",
   "parent": null,
   "parentfield": null,
   "parenttype": null,
   "permlevel": 0,
   "precision": "",
   "print_hide": 0,
   "print_hide_if_no_value": 0,
   "print_width": null,
   "read_only": 0,
   "report_hide": 0,
   "reqd": 0,
   "search_index": 0,
   "translatable": 0,
   "unique": 0,
   "width": null
  },
  {
   "_assign": null,
   "_comments": null,
   "_liked_by": null,
   "_user_tags": null,
   "allow_in_quick_entry": 0,
   "allow_on_submit": 0,
   "bold": 0,
   "collapsible": 0,
   "collapsible_depends_on": null,
   "columns": 0,
   "creation": "2019-05-10 20:33:45.999263",
   "default": null,
   "depends_on": "eval:in_list([\"RI Desk\",\"TRIO*\",\"New Trio\",\"Fox\",\"Counter\"], doc.item_group)",
   "description": null,
   "docstatus": 0,
   "dt": "Material Request Item",
   "fetch_from": null,
   "fetch_if_empty": 0,
   "fieldname": "pvc",
   "fieldtype": "Link",
   "hidden": 0,
   "idx": 10,
   "ignore_user_permissions": 0,
   "ignore_xss_filter": 0,
   "in_filter": 0,
   "in_filter_dash": 0,
   "in_global_search": 0,
   "in_list_view": 0,
   "in_standard_filter": 0,
   "insert_after": "or",
   "label": "PVC",
   "length": 0,
   "modified": "2019-05-10 20:33:45.999263",
   "modified_by": "Administrator",
   "name": "Material Request Item-pvc",
   "no_copy": 0,
   "options": "PVC",
   "owner": "Administrator",
   "parent": null,
   "parentfield": null,
   "parenttype": null,
   "permlevel": 0,
   "precision": "",
   "print_hide": 0,
   "print_hide_if_no_value": 0,
   "print_width": null,
   "read_only": 0,
   "report_hide": 0,
   "reqd": 0,
   "search_index": 0,
   "translatable": 0,
   "unique": 0,
   "width": null
  },
  {
   "_assign": null,
   "_comments": null,
   "_liked_by": null,
   "_user_tags": null,
   "allow_in_quick_entry": 0,
   "allow_on_submit": 0,
   "bold": 0,
   "collapsible": 0,
   "collapsible_depends_on": null,
   "columns": 0,
   "creation": "2019-05-10 20:34:03.942764",
   "default": null,
   "depends_on": "eval:doc.item_group == \"Quatro\"",
   "description": null,
   "docstatus": 0,
   "dt": "Material Request Item",
   "fetch_from": null,
   "fetch_if_empty": 0,
   "fieldname": "quatro",
   "fieldtype": "Link",
   "hidden": 0,
   "idx": 11,
   "ignore_user_permissions": 0,
   "ignore_xss_filter": 0,
   "in_filter": 0,
   "in_filter_dash": 0,
   "in_global_search": 0,
   "in_list_view": 0,
   "in_standard_filter": 0,
   "insert_after": "pvc",
   "label": "Quatro",
   "length": 0,
   "modified": "2019-05-10 20:34:03.942764",
   "modified_by": "Administrator",
   "name": "Material Request Item-quatro",
   "no_copy": 0,
   "options": "Quatro",
   "owner": "Administrator",
   "parent": null,
   "parentfield": null,
   "parenttype": null,
   "permlevel": 0,
   "precision": "",
   "print_hide": 0,
   "print_hide_if_no_value": 0,
   "print_width": null,
   "read_only": 0,
   "report_hide": 0,
   "reqd": 0,
   "search_index": 0,
   "translatable": 0,
   "unique": 0,
   "width": null
  },
  {
   "_assign": null,
   "_comments": null,
   "_liked_by": null,
   "_user_tags": null,
   "allow_in_quick_entry": 0,
   "allow_on_submit": 0,
   "bold": 0,
   "collapsible": 0,
   "collapsible_depends_on": null,
   "columns": 0,
   "creation": "2019-05-10 20:34:15.551699",
   "default": null,
   "depends_on": "eval:doc.item_group == \"R Desk\"",
   "description": null,
   "docstatus": 0,
   "dt": "Material Request Item",
   "fetch_from": null,
   "fetch_if_empty": 0,
   "fieldname": "r_desk",
   "fieldtype": "Link",
   "hidden": 0,
   "idx": 12,
   "ignore_user_permissions": 0,
   "ignore_xss_filter": 0,
   "in_filter": 0,
   "in_filter_dash": 0,
   "in_global_search": 0,
   "in_list_view": 0,
   "in_standard_filter": 0,
   "insert_after": "quatro",
   "label": "R_Desk",
   "length": 0,
   "modified": "2019-05-10 20:34:15.551699",
   "modified_by": "Administrator",
   "name": "Material Request Item-r_desk",
   "no_copy": 0,
   "options": "R_Desk",
   "owner": "Administrator",
   "parent": null,
   "parentfield": null,
   "parenttype": null,
   "permlevel": 0,
   "precision": "",
   "print_hide": 0,
   "print_hide_if_no_value": 0,
   "print_width": null,
   "read_only": 0,
   "report_hide": 0,
   "reqd": 0,
   "search_index": 0,
   "translatable": 0,
   "unique": 0,
   "width": null
  },
  {
   "_assign": null,
   "_comments": null,
   "_liked_by": null,
   "_user_tags": null,
   "allow_in_quick_entry": 0,
   "allow_on_submit": 0,
   "bold": 0,
   "collapsible": 0,
   "collapsible_depends_on": null,
   "columns": 0,
   "creation": "2019-05-10 20:34:35.161415",
   "default": null,
   "depends_on": "eval:doc.item_group == \"SLIM\"",
   "description": null,
   "docstatus": 0,
   "dt": "Material Request Item",
   "fetch_from": null,
   "fetch_if_empty": 0,
   "fieldname": "slim",
   "fieldtype": "Link",
   "hidden": 0,
   "idx": 13,
   "ignore_user_permissions": 0,
   "ignore_xss_filter": 0,
   "in_filter": 0,
   "in_filter_dash": 0,
   "in_global_search": 0,
   "in_list_view": 0,
   "in_standard_filter": 0,
   "insert_after": "r_desk",
   "label": "Slim",
   "length": 0,
   "modified": "2019-05-10 20:34:35.161415",
   "modified_by": "Administrator",
   "name": "Material Request Item-slim",
   "no_copy": 0,
   "options": "Slim",
   "owner": "Administrator",
   "parent": null,
   "parentfield": null,
   "parenttype": null,
   "permlevel": 0,
   "precision": "",
   "print_hide": 0,
   "print_hide_if_no_value": 0,
   "print_width": null,
   "read_only": 0,
   "report_hide": 0,
   "reqd": 0,
   "search_index": 0,
   "translatable": 0,
   "unique": 0,
   "width": null
  },
  {
   "_assign": null,
   "_comments": null,
   "_liked_by": null,
   "_user_tags": null,
   "allow_in_quick_entry": 0,
   "allow_on_submit": 0,
   "bold": 0,
   "collapsible": 0,
   "collapsible_depends_on": null,
   "columns": 0,
   "creation": "2019-05-10 20:34:51.462750",
   "default": null,
   "depends_on": "eval:doc.item_group == \"STEP\"",
   "description": null,
   "docstatus": 0,
   "dt": "Material Request Item",
   "fetch_from": null,
   "fetch_if_empty": 0,
   "fieldname": "step",
   "fieldtype": "Link",
   "hidden": 0,
   "idx": 14,
   "ignore_user_permissions": 0,
   "ignore_xss_filter": 0,
   "in_filter": 0,
   "in_filter_dash": 0,
   "in_global_search": 0,
   "in_list_view": 0,
   "in_standard_filter": 0,
   "insert_after": "slim",
   "label": "Step",
   "length": 0,
   "modified": "2019-05-10 20:34:51.462750",
   "modified_by": "Administrator",
   "name": "Material Request Item-step",
   "no_copy": 0,
   "options": "Step",
   "owner": "Administrator",
   "parent": null,
   "parentfield": null,
   "parenttype": null,
   "permlevel": 0,
   "precision": "",
   "print_hide": 0,
   "print_hide_if_no_value": 0,
   "print_width": null,
   "read_only": 0,
   "report_hide": 0,
   "reqd": 0,
   "search_index": 0,
   "translatable": 0,
   "unique": 0,
   "width": null
  },
  {
   "_assign": null,
   "_comments": null,
   "_liked_by": null,
   "_user_tags": null,
   "allow_in_quick_entry": 0,
   "allow_on_submit": 0,
   "bold": 0,
   "collapsible": 0,
   "collapsible_depends_on": null,
   "columns": 0,
   "creation": "2019-05-10 20:35:01.807304",
   "default": null,
   "depends_on": "eval:doc.item_group == \"T Desk\"",
   "description": null,
   "docstatus": 0,
   "dt": "Material Request Item",
   "fetch_from": null,
   "fetch_if_empty": 0,
   "fieldname": "t_desk",
   "fieldtype": "Link",
   "hidden": 0,
   "idx": 15,
   "ignore_user_permissions": 0,
   "ignore_xss_filter": 0,
   "in_filter": 0,
   "in_filter_dash": 0,
   "in_global_search": 0,
   "in_list_view": 0,
   "in_standard_filter": 0,
   "insert_after": "step",
   "label": "T_Desk",
   "length": 0,
   "modified": "2019-05-10 20:35:01.807304",
   "modified_by": "Administrator",
   "name": "Material Request Item-t_desk",
   "no_copy": 0,
   "options": "T_Desk",
   "owner": "Administrator",
   "parent": null,
   "parentfield": null,
   "parenttype": null,
   "permlevel": 0,
   "precision": "",
   "print_hide": 0,
   "print_hide_if_no_value": 0,
   "print_width": null,
   "read_only": 0,
   "report_hide": 0,
   "reqd": 0,
   "search_index": 0,
   "translatable": 0,
   "unique": 0,
   "width": null
  },
  {
   "_assign": null,
   "_comments": null,
   "_liked_by": null,
   "_user_tags": null,
   "allow_in_quick_entry": 0,
   "allow_on_submit": 0,
   "bold": 0,
   "collapsible": 0,
   "collapsible_depends_on": null,
   "columns": 0,
   "creation": "2019-06-29 14:04:00.246394",
   "default": null,
   "depends_on": null,
   "description": null,
   "docstatus": 0,
   "dt": "Material Request Item",
   "fetch_from": null,
   "fetch_if_empty": 0,
   "fieldname": "metal",
   "fieldtype": "Check",
   "hidden": 1,
   "idx": 4,
   "ignore_user_permissions": 0,
   "ignore_xss_filter": 0,
   "in_filter": 0,
   "in_filter_dash": 0,
   "in_global_search": 0,
   "in_list_view": 0,
   "in_standard_filter": 0,
   "insert_after": "base_color",
   "label": "Metal",
   "length": 0,
   "modified": "2019-06-29 14:04:00.246394",
   "modified_by": "Administrator",
   "name": "Material Request Item-metal",
   "no_copy": 0,
   "options": null,
   "owner": "Administrator",
   "parent": null,
   "parentfield": null,
   "parenttype": null,
   "permlevel": 0,
   "precision": "",
   "print_hide": 0,
   "print_hide_if_no_value": 0,
   "print_width": null,
   "read_only": 0,
   "report_hide": 0,
   "reqd": 0,
   "search_index": 0,
   "translatable": 0,
   "unique": 0,
   "width": null
  },
  {
   "_assign": null,
   "_comments": null,
   "_liked_by": null,
   "_user_tags": null,
   "allow_in_quick_entry": 0,
   "allow_on_submit": 0,
   "bold": 0,
   "collapsible": 0,
   "collapsible_depends_on": null,
   "columns": 0,
   "creation": "2019-06-29 14:04:14.517328",
   "default": null,
   "depends_on": null,
   "description": null,
   "docstatus": 0,
   "dt": "Material Request Item",
   "fetch_from": null,
   "fetch_if_empty": 0,
   "fieldname": "metal_color",
   "fieldtype": "Link",
   "hidden": 0,
   "idx": 5,
   "ignore_user_permissions": 0,
   "ignore_xss_filter": 0,
   "in_filter": 0,
   "in_filter_dash": 0,
   "in_global_search": 0,
   "in_list_view": 0,
   "in_standard_filter": 0,
   "insert_after": "metal",
   "label": "Metal Color",
   "length": 0,
   "modified": "2019-06-29 14:04:14.517328",
   "modified_by": "Administrator",
   "name": "Material Request Item-metal_color",
   "no_copy": 0,
   "options": "Metal Color",
   "owner": "Administrator",
   "parent": null,
   "parentfield": null,
   "parenttype": null,
   "permlevel": 0,
   "precision": "",
   "print_hide": 0,
   "print_hide_if_no_value": 0,
   "print_width": null,
   "read_only": 0,
   "report_hide": 0,
   "reqd": 0,
   "search_index": 0,
   "translatable": 0,
   "unique": 0,
   "width": null
  },
  {
   "_assign": null,
   "_comments": null,
   "_liked_by": null,
   "_user_tags": null,
   "allow_in_quick_entry": 0,
   "allow_on_submit": 0,
   "bold": 0,
   "collapsible": 0,
   "collapsible_depends_on": null,
   "columns": 0,
   "creation": "2019-12-31 17:49:12.398069",
   "default": null,
   "depends_on": null,
   "description": null,
   "docstatus": 0,
   "dt": "Material Request Item",
   "fetch_from": null,
   "fetch_if_empty": 0,
   "fieldname": "territory",
   "fieldtype": "Link",
   "hidden": 0,
   "idx": 66,
   "ignore_user_permissions": 0,
   "ignore_xss_filter": 0,
   "in_filter": 0,
   "in_filter_dash": 0,
   "in_global_search": 0,
   "in_list_view": 0,
   "in_standard_filter": 0,
   "insert_after": "accounting_dimensions_section",
   "label": "Territory",
   "length": 0,
   "modified": "2020-04-15 10:05:18.756289",
   "modified_by": "it.depart@riadco.com",
   "name": "Material Request Item-territory",
   "no_copy": 0,
   "options": "Territory",
   "owner": "Administrator",
   "parent": null,
   "parentfield": null,
   "parenttype": null,
   "permlevel": 0,
   "precision": "",
   "print_hide": 0,
   "print_hide_if_no_value": 0,
   "print_width": null,
   "read_only": 0,
   "report_hide": 0,
   "reqd": 0,
   "search_index": 0,
   "translatable": 0,
   "unique": 0,
   "width": null
  },
  {
   "_assign": null,
   "_comments": null,
   "_liked_by": null,
   "_user_tags": null,
   "allow_in_quick_entry": 0,
   "allow_on_submit": 0,
   "bold": 0,
   "collapsible": 0,
   "collapsible_depends_on": null,
   "columns": 0,
   "creation": "2020-10-25 17:19:46.093252",
   "default": null,
   "depends_on": null,
   "description": null,
   "docstatus": 0,
   "dt": "Material Request Item",
   "fetch_from": null,
   "fetch_if_empty": 0,
   "fieldname": "workstation",
   "fieldtype": "Section Break",
   "hidden": 0,
   "idx": 19,
   "ignore_user_permissions": 0,
   "ignore_xss_filter": 0,
   "in_filter": 0,
   "in_filter_dash": 0,
   "in_global_search": 0,
   "in_list_view": 0,
   "in_standard_filter": 0,
   "insert_after": "notes",
   "label": "Workstation",
   "length": 0,
   "modified": "2020-10-25 17:19:46.093252",
   "modified_by": "Administrator",
   "name": "Material Request Item-workstation",
   "no_copy": 0,
   "options": null,
   "owner": "Administrator",
   "parent": null,
   "parentfield": null,
   "parenttype": null,
   "permlevel": 0,
   "precision": "",
   "print_hide": 0,
   "print_hide_if_no_value": 0,
   "print_width": null,
   "read_only": 0,
   "report_hide": 0,
   "reqd": 0,
   "search_index": 0,
   "translatable": 0,
   "unique": 0,
   "width": null
  },
  {
   "_assign": null,
   "_comments": null,
   "_liked_by": null,
   "_user_tags": null,
   "allow_in_quick_entry": 0,
   "allow_on_submit": 0,
   "bold": 0,
   "collapsible": 0,
   "collapsible_depends_on": null,
   "columns": 0,
   "creation": "2020-10-25 17:19:46.592508",
   "default": null,
   "depends_on": null,
   "description": null,
   "docstatus": 0,
   "dt": "Material Request Item",
   "fetch_from": null,
   "fetch_if_empty": 0,
   "fieldname": "imported_ws",
   "fieldtype": "Check",
   "hidden": 0,
   "idx": 20,
   "ignore_user_permissions": 0,
   "ignore_xss_filter": 0,
   "in_filter": 0,
   "in_filter_dash": 0,
   "in_global_search": 0,
   "in_list_view": 0,
   "in_standard_filter": 0,
   "insert_after": "workstation",
   "label": "\u0645\u0633\u062a\u0648\u0631\u062f",
   "length": 0,
   "modified": "2020-10-25 17:19:46.592508",
   "modified_by": "Administrator",
   "name": "Material Request Item-imported_ws",
   "no_copy": 0,
   "options": null,
   "owner": "Administrator",
   "parent": null,
   "parentfield": null,
   "parenttype": null,
   "permlevel": 0,
   "precision": "",
   "print_hide": 0,
   "print_hide_if_no_value": 0,
   "print_width": null,
   "read_only": 0,
   "report_hide": 0,
   "reqd": 0,
   "search_index": 0,
   "translatable": 0,
   "unique": 0,
   "width": null
  },
  {
   "_assign": null,
   "_comments": null,
   "_liked_by": null,
   "_user_tags": null,
   "allow_in_quick_entry": 0,
   "allow_on_submit": 0,
   "bold": 0,
   "collapsible": 0,
   "collapsible_depends_on": null,
   "columns": 0,
   "creation": "2020-10-25 17:19:53.539522",
   "default": null,
   "depends_on": null,
   "description": null,
   "docstatus": 0,
   "dt": "Material Request Item",
   "fetch_from": null,
   "fetch_if_empty": 0,
   "fieldname": "supplier_ws",
   "fieldtype": "Check",
   "hidden": 0,
   "idx": 21,
   "ignore_user_permissions": 0,
   "ignore_xss_filter": 0,
   "in_filter": 0,
   "in_filter_dash": 0,
   "in_global_search": 0,
   "in_list_view": 0,
   "in_standard_filter": 0,
   "insert_after": "imported_ws",
   "label": "\u0645\u0648\u0631\u062f \u062e\u0627\u0631\u062c\u064a",
   "length": 0,
   "modified": "2020-10-25 17:19:53.539522",
   "modified_by": "Administrator",
   "name": "Material Request Item-supplier_ws",
   "no_copy": 0,
   "options": null,
   "owner": "Administrator",
   "parent": null,
   "parentfield": null,
   "parenttype": null,
   "permlevel": 0,
   "precision": "",
   "print_hide": 0,
   "print_hide_if_no_value": 0,
   "print_width": null,
   "read_only": 0,
   "report_hide": 0,
   "reqd": 0,
   "search_index": 0,
   "translatable": 0,
   "unique": 0,
   "width": null
  },
  {
   "_assign": null,
   "_comments": null,
   "_liked_by": null,
   "_user_tags": null,
   "allow_in_quick_entry": 0,
   "allow_on_submit": 0,
   "bold": 0,
   "collapsible": 0,
   "collapsible_depends_on": null,
   "columns": 0,
   "creation": "2020-10-25 17:19:59.474044",
   "default": null,
   "depends_on": null,
   "description": null,
   "docstatus": 0,
   "dt": "Material Request Item",
   "fetch_from": null,
   "fetch_if_empty": 0,
   "fieldname": "artificial_ws",
   "fieldtype": "Check",
   "hidden": 0,
   "idx": 22,
   "ignore_user_permissions": 0,
   "ignore_xss_filter": 0,
   "in_filter": 0,
   "in_filter_dash": 0,
   "in_global_search": 0,
   "in_list_view": 0,
   "in_standard_filter": 0,
   "insert_after": "supplier_ws",
   "label": "\u0635\u0646\u0627\u0639\u064a",
   "length": 0,
   "modified": "2020-10-25 17:19:59.474044",
   "modified_by": "Administrator",
   "name": "Material Request Item-artificial_ws",
   "no_copy": 0,
   "options": null,
   "owner": "Administrator",
   "parent": null,
   "parentfield": null,
   "parenttype": null,
   "permlevel": 0,
   "precision": "",
   "print_hide": 0,
   "print_hide_if_no_value": 0,
   "print_width": null,
   "read_only": 0,
   "report_hide": 0,
   "reqd": 0,
   "search_index": 0,
   "translatable": 0,
   "unique": 0,
   "width": null
  },
  {
   "_assign": null,
   "_comments": null,
   "_liked_by": null,
   "_user_tags": null,
   "allow_in_quick_entry": 0,
   "allow_on_submit": 0,
   "bold": 0,
   "collapsible": 0,
   "collapsible_depends_on": null,
   "columns": 0,
   "creation": "2020-10-25 17:20:05.514408",
   "default": null,
   "depends_on": null,
   "description": null,
   "docstatus": 0,
   "dt": "Material Request Item",
   "fetch_from": null,
   "fetch_if_empty": 0,
   "fieldname": "natural_ws",
   "fieldtype": "Check",
   "hidden": 0,
   "idx": 23,
   "ignore_user_permissions": 0,
   "ignore_xss_filter": 0,
   "in_filter": 0,
   "in_filter_dash": 0,
   "in_global_search": 0,
   "in_list_view": 0,
   "in_standard_filter": 0,
   "insert_after": "artificial_ws",
   "label": "\u0637\u0628\u064a\u0639\u064a",
   "length": 0,
   "modified": "2020-10-25 17:20:05.514408",
   "modified_by": "Administrator",
   "name": "Material Request Item-natural_ws",
   "no_copy": 0,
   "options": null,
   "owner": "Administrator",
   "parent": null,
   "parentfield": null,
   "parenttype": null,
   "permlevel": 0,
   "precision": "",
   "print_hide": 0,
   "print_hide_if_no_value": 0,
   "print_width": null,
   "read_only": 0,
   "report_hide": 0,
   "reqd": 0,
   "search_index": 0,
   "translatable": 0,
   "unique": 0,
   "width": null
  },
  {
   "_assign": null,
   "_comments": null,
   "_liked_by": null,
   "_user_tags": null,
   "allow_in_quick_entry": 0,
   "allow_on_submit": 0,
   "bold": 0,
   "collapsible": 0,
   "collapsible_depends_on": null,
   "columns": 0,
   "creation": "2020-10-25 17:20:11.929251",
   "default": null,
   "depends_on": null,
   "description": null,
   "docstatus": 0,
   "dt": "Material Request Item",
   "fetch_from": null,
   "fetch_if_empty": 0,
   "fieldname": "column_break_23",
   "fieldtype": "Column Break",
   "hidden": 0,
   "idx": 24,
   "ignore_user_permissions": 0,
   "ignore_xss_filter": 0,
   "in_filter": 0,
   "in_filter_dash": 0,
   "in_global_search": 0,
   "in_list_view": 0,
   "in_standard_filter": 0,
   "insert_after": "natural_ws",
   "label": null,
   "length": 0,
   "modified": "2020-10-25 17:20:11.929251",
   "modified_by": "Administrator",
   "name": "Material Request Item-column_break_23",
   "no_copy": 0,
   "options": null,
   "owner": "Administrator",
   "parent": null,
   "parentfield": null,
   "parenttype": null,
   "permlevel": 0,
   "precision": "",
   "print_hide": 0,
   "print_hide_if_no_value": 0,
   "print_width": null,
   "read_only": 0,
   "report_hide": 0,
   "reqd": 0,
   "search_index": 0,
   "translatable": 0,
   "unique": 0,
   "width": null
  },
  {
   "_assign": null,
   "_comments": null,
   "_liked_by": null,
   "_user_tags": null,
   "allow_in_quick_entry": 0,
   "allow_on_submit": 0,
   "bold": 0,
   "collapsible": 0,
   "collapsible_depends_on": null,
   "columns": 0,
   "creation": "2020-10-25 17:20:12.947456",
   "default": null,
   "depends_on": null,
   "description": null,
   "docstatus": 0,
   "dt": "Material Request Item",
   "fetch_from": null,
   "fetch_if_empty": 0,
   "fieldname": "leather_ws",
   "fieldtype": "Check",
   "hidden": 0,
   "idx": 25,
   "ignore_user_permissions": 0,
   "ignore_xss_filter": 0,
   "in_filter": 0,
   "in_filter_dash": 0,
   "in_global_search": 0,
   "in_list_view": 0,
   "in_standard_filter": 0,
   "insert_after": "column_break_23",
   "label": "\u062a\u0646\u062c\u064a\u062f",
   "length": 0,
   "modified": "2020-10-25 17:20:12.947456",
   "modified_by": "Administrator",
   "name": "Material Request Item-leather_ws",
   "no_copy": 0,
   "options": null,
   "owner": "Administrator",
   "parent": null,
   "parentfield": null,
   "parenttype": null,
   "permlevel": 0,
   "precision": "",
   "print_hide": 0,
   "print_hide_if_no_value": 0,
   "print_width": null,
   "read_only": 0,
   "report_hide": 0,
   "reqd": 0,
   "search_index": 0,
   "translatable": 0,
   "unique": 0,
   "width": null
  },
  {
   "_assign": null,
   "_comments": null,
   "_liked_by": null,
   "_user_tags": null,
   "allow_in_quick_entry": 0,
   "allow_on_submit": 0,
   "bold": 0,
   "collapsible": 0,
   "collapsible_depends_on": null,
   "columns": 0,
   "creation": "2020-10-25 17:20:29.909703",
   "default": null,
   "depends_on": null,
   "description": null,
   "docstatus": 0,
   "dt": "Material Request Item",
   "fetch_from": null,
   "fetch_if_empty": 0,
   "fieldname": "accessories_ws",
   "fieldtype": "Check",
   "hidden": 0,
   "idx": 26,
   "ignore_user_permissions": 0,
   "ignore_xss_filter": 0,
   "in_filter": 0,
   "in_filter_dash": 0,
   "in_global_search": 0,
   "in_list_view": 0,
   "in_standard_filter": 0,
   "insert_after": "leather_ws",
   "label": "\u0627\u0643\u0633\u0633\u0648\u0627\u0631",
   "length": 0,
   "modified": "2020-10-25 17:20:29.909703",
   "modified_by": "Administrator",
   "name": "Material Request Item-accessories_ws",
   "no_copy": 0,
   "options": null,
   "owner": "Administrator",
   "parent": null,
   "parentfield": null,
   "parenttype": null,
   "permlevel": 0,
   "precision": "",
   "print_hide": 0,
   "print_hide_if_no_value": 0,
   "print_width": null,
   "read_only": 0,
   "report_hide": 0,
   "reqd": 0,
   "search_index": 0,
   "translatable": 0,
   "unique": 0,
   "width": null
  },
  {
   "_assign": null,
   "_comments": null,
   "_liked_by": null,
   "_user_tags": null,
   "allow_in_quick_entry": 0,
   "allow_on_submit": 0,
   "bold": 0,
   "collapsible": 0,
   "collapsible_depends_on": null,
   "columns": 0,
   "creation": "2020-10-25 17:20:39.609634",
   "default": null,
   "depends_on": null,
   "description": null,
   "docstatus": 0,
   "dt": "Material Request Item",
   "fetch_from": null,
   "fetch_if_empty": 0,
   "fieldname": "metal_ws",
   "fieldtype": "Check",
   "hidden": 0,
   "idx": 27,
   "ignore_user_permissions": 0,
   "ignore_xss_filter": 0,
   "in_filter": 0,
   "in_filter_dash": 0,
   "in_global_search": 0,
   "in_list_view": 0,
   "in_standard_filter": 0,
   "insert_after": "accessories_ws",
   "label": "\u0645\u0639\u0627\u062f\u0646",
   "length": 0,
   "modified": "2020-10-25 17:20:39.609634",
   "modified_by": "Administrator",
   "name": "Material Request Item-metal_ws",
   "no_copy": 0,
   "options": null,
   "owner": "Administrator",
   "parent": null,
   "parentfield": null,
   "parenttype": null,
   "permlevel": 0,
   "precision": "",
   "print_hide": 0,
   "print_hide_if_no_value": 0,
   "print_width": null,
   "read_only": 0,
   "report_hide": 0,
   "reqd": 0,
   "search_index": 0,
   "translatable": 0,
   "unique": 0,
   "width": null
  }
 ],
 "custom_perms": [],
 "doctype": "Material Request Item",
 "property_setters": [
  {
   "_assign": null,
   "_comments": null,
   "_liked_by": null,
   "_user_tags": null,
   "creation": "2020-11-29 11:14:31.314958",
   "default_value": null,
   "doc_type": "Material Request Item",
   "docstatus": 0,
   "doctype_or_field": "DocField",
   "field_name": "item_name",
   "idx": 0,
   "modified": "2020-11-29 11:14:31.314958",
   "modified_by": "it.depart@riadco.com",
   "name": "Material Request Item-item_name-read_only",
   "owner": "it.depart@riadco.com",
   "parent": null,
   "parentfield": null,
   "parenttype": null,
   "property": "read_only",
   "property_type": "Check",
   "value": "1"
  },
  {
   "_assign": null,
   "_comments": null,
   "_liked_by": null,
   "_user_tags": null,
   "creation": "2019-02-10 17:30:55.605594",
   "default_value": null,
   "doc_type": "Material Request Item",
   "docstatus": 0,
   "doctype_or_field": "DocField",
   "field_name": "warehouse",
   "idx": 0,
   "modified": "2019-02-10 17:30:55.605594",
   "modified_by": "Administrator",
   "name": "Material Request Item-warehouse-columns",
   "owner": "Administrator",
   "parent": null,
   "parentfield": null,
   "parenttype": null,
   "property": "columns",
   "property_type": "Int",
   "value": "2"
  },
  {
   "_assign": null,
   "_comments": null,
   "_liked_by": null,
   "_user_tags": null,
   "creation": "2019-02-10 17:30:55.576128",
   "default_value": null,
   "doc_type": "Material Request Item",
   "docstatus": 0,
   "doctype_or_field": "DocField",
   "field_name": "qty",
   "idx": 0,
   "modified": "2019-02-10 17:30:55.576128",
   "modified_by": "Administrator",
   "name": "Material Request Item-qty-columns",
   "owner": "Administrator",
   "parent": null,
   "parentfield": null,
   "parenttype": null,
   "property": "columns",
   "property_type": "Int",
   "value": "1"
  },
  {
   "_assign": null,
   "_comments": null,
   "_liked_by": null,
   "_user_tags": null,
   "creation": "2017-11-20 11:28:19.365167",
   "default_value": null,
   "doc_type": "Material Request Item",
   "docstatus": 0,
   "doctype_or_field": "DocField",
   "field_name": "item_name",
   "idx": 0,
   "modified": "2017-11-20 11:28:19.365167",
   "modified_by": "store.manager@riadco.com",
   "name": "Material Request Item-item_name-width",
   "owner": "store.manager@riadco.com",
   "parent": null,
   "parentfield": null,
   "parenttype": null,
   "property": "width",
   "property_type": null,
   "value": "254"
  },
  {
   "_assign": null,
   "_comments": null,
   "_liked_by": null,
   "_user_tags": null,
   "creation": "2017-11-20 11:28:19.350345",
   "default_value": null,
   "doc_type": "Material Request Item",
   "docstatus": 0,
   "doctype_or_field": "DocField",
   "field_name": "item_code",
   "idx": 0,
   "modified": "2017-11-20 11:28:19.350345",
   "modified_by": "store.manager@riadco.com",
   "name": "Material Request Item-item_code-width",
   "owner": "store.manager@riadco.com",
   "parent": null,
   "parentfield": null,
   "parenttype": null,
   "property": "width",
   "property_type": null,
   "value": "96"
  },
  {
   "_assign": null,
   "_comments": null,
   "_liked_by": null,
   "_user_tags": null,
   "creation": "2017-09-27 11:01:09.477141",
   "default_value": null,
   "doc_type": "Material Request Item",
   "docstatus": 0,
   "doctype_or_field": "DocField",
   "field_name": "projected_qty",
   "idx": 0,
   "modified": "2017-09-27 11:01:09.477141",
   "modified_by": "Administrator",
   "name": "Material Request Item-projected_qty-width",
   "owner": "Administrator",
   "parent": null,
   "parentfield": null,
   "parenttype": null,
   "property": "width",
   "property_type": null,
   "value": "98"
  },
  {
   "_assign": null,
   "_comments": null,
   "_liked_by": null,
   "_user_tags": null,
   "creation": "2017-05-31 02:44:42.383797",
   "default_value": null,
   "doc_type": "Material Request Item",
   "docstatus": 0,
   "doctype_or_field": "DocField",
   "field_name": "schedule_date",
   "idx": 0,
   "modified": "2017-05-31 02:44:42.383797",
   "modified_by": "Administrator",
   "name": "Material Request Item-schedule_date-in_list_view",
   "owner": "Administrator",
   "parent": null,
   "parentfield": null,
   "parenttype": null,
   "property": "in_list_view",
   "property_type": "Check",
   "value": "0"
  },
  {
   "_assign": null,
   "_comments": null,
   "_liked_by": null,
   "_user_tags": null,
   "creation": "2017-05-31 02:44:25.080528",
   "default_value": null,
   "doc_type": "Material Request Item",
   "docstatus": 0,
   "doctype_or_field": "DocField",
   "field_name": "item_name",
   "idx": 0,
   "modified": "2017-05-31 02:44:25.080528",
   "modified_by": "Administrator",
   "name": "Material Request Item-item_name-in_list_view",
   "owner": "Administrator",
   "parent": null,
   "parentfield": null,
   "parenttype": null,
   "property": "in_list_view",
   "property_type": "Check",
   "value": "1"
  },
  {
   "_assign": null,
   "_comments": null,
   "_liked_by": null,
   "_user_tags": null,
   "creation": "2017-05-17 01:00:26.499289",
   "default_value": null,
   "doc_type": "Material Request Item",
   "docstatus": 0,
   "doctype_or_field": "DocField",
   "field_name": "schedule_date",
   "idx": 0,
   "modified": "2017-05-17 01:00:26.499289",
   "modified_by": "Administrator",
   "name": "Material Request Item-schedule_date-reqd",
   "owner": "Administrator",
   "parent": null,
   "parentfield": null,
   "parenttype": null,
   "property": "reqd",
   "property_type": "Check",
   "value": "0"
  },
  {
   "_assign": null,
   "_comments": null,
   "_liked_by": null,
   "_user_tags": null,
   "creation": "2017-05-16 17:28:46.527120",
   "default_value": null,
   "doc_type": "Material Request Item",
   "docstatus": 0,
   "doctype_or_field": "DocType",
   "field_name": null,
   "idx": 0,
   "modified": "2017-05-16 17:28:46.527120",
   "modified_by": "islam.mayo@gmail.com",
   "name": "Material Request Item-sort_field",
   "owner": "islam.mayo@gmail.com",
   "parent": null,
   "parentfield": null,
   "parenttype": null,
   "property": "sort_field",
   "property_type": "Data",
   "value": "modified"
  }
 ],
 "sync_on_migrate": 1
}